bimvee/__init__.py
bimvee/container.py
bimvee/events.py
bimvee/exportHdf5.py
bimvee/exportIitYarp.py
bimvee/exportPoseRpgEsimCsv.py
bimvee/exportRpgDvsRos.py
bimvee/geometry.py
bimvee/importAe.py
bimvee/importAer2.py
bimvee/importExportBatches.py
bimvee/importFrames.py
bimvee/importHdf5.py
bimvee/importIitNumpy.py
bimvee/importIitVicon.py
bimvee/importIitYarp.py
bimvee/importProph.py
bimvee/importRpgDvsRos.py
bimvee/importSecDvs.py
bimvee/info.py
bimvee/plot.py
bimvee/plotCorrelogram.py
bimvee/plotDvsContrast.py
bimvee/plotDvsLastTs.py
bimvee/plotDvsSpaceTime.py
bimvee/plotEventRate.py
bimvee/plotFlow.py
bimvee/plotFrame.py
bimvee/plotImu.py
bimvee/plotPose.py
bimvee/plotSpikeogram.py
bimvee/pose.py
bimvee/split.py
bimvee/timestamps.py
bimvee/visualiser.py
bimvee/importRosbag/importRosbag/__init__.py
bimvee/importRosbag/importRosbag/importRosbag.py
bimvee/importRosbag/importRosbag/messageTypes/common.py
bimvee/importRosbag/importRosbag/messageTypes/dvs_msgs_EventArray.py
bimvee/importRosbag/importRosbag/messageTypes/esim_msgs_OpticFlow.py
bimvee/importRosbag/importRosbag/messageTypes/geometry_msgs_PoseStamped.py
bimvee/importRosbag/importRosbag/messageTypes/geometry_msgs_Transform.py
bimvee/importRosbag/importRosbag/messageTypes/geometry_msgs_TransformStamped.py
bimvee/importRosbag/importRosbag/messageTypes/geometry_msgs_TwistStamped.py
bimvee/importRosbag/importRosbag/messageTypes/sensor_msgs_CameraInfo.py
bimvee/importRosbag/importRosbag/messageTypes/sensor_msgs_Image.py
bimvee/importRosbag/importRosbag/messageTypes/sensor_msgs_Imu.py
bimvee/importRosbag/importRosbag/messageTypes/sensor_msgs_PointCloud2.py
bimvee/importRosbag/importRosbag/messageTypes/tf_tfMessage.py
bimvee-1.0.10.dist-info/LICENSE.txt
bimvee-1.0.10.dist-info/METADATA
bimvee-1.0.10.dist-info/WHEEL
bimvee-1.0.10.dist-info/top_level.txt
bimvee-1.0.10.dist-info/RECORD
