Metadata-Version: 2.1
Name: bimvee
Version: 1.0.10
Summary: Batch Import, Manipulation, Visualisation and Export of Events etc
Home-page: https://github.com/event-driven-robotics/bimvee
Author: Event-driven Perception for Robotics group at Istituto Italiano di Tecnologia: Simeon Bamford, Suman Ghosh, Aiko Dinale, Massimiliano Iaconi, Ander Arriandiaga, etc
Author-email: simbamford@gmail.com
License: gpl
Download-URL: https://github.com/event-driven-robotics/bimvee_pkg/archive/v1.0.tar.gz
Keywords: event,event camera,event-based,event-driven,spike,dvs,dynamic vision sensor,neuromorphic,aer,address-event representationspiking neural network,davis,atis,celex
Platform: UNKNOWN
Classifier: Development Status :: 3 - Alpha
Classifier: Intended Audience :: Developers
Classifier: Topic :: Software Development :: Build Tools
Classifier: License :: OSI Approved :: GNU General Public License (GPL)
Classifier: Programming Language :: Python :: 3
Classifier: Programming Language :: Python :: 3.7
Requires-Dist: numpy
Requires-Dist: tqdm
Requires-Dist: setuptools
Requires-Dist: matplotlib
Requires-Dist: seaborn
Requires-Dist: imageio
Requires-Dist: hickle
